lifx_control_panel/__init__.py
lifx_control_panel/__main__.pyw
lifx_control_panel/_constants.py
lifx_control_panel/sign_all.py
lifx_control_panel/tests/__init__.py
lifx_control_panel/tests/dummy_devices.py
lifx_control_panel/tests/dummy_tests.py
lifx_control_panel/ui/SysTrayIcon.py
lifx_control_panel/ui/__init__.py
lifx_control_panel/ui/colorscale.py
lifx_control_panel/ui/icon_list.py
lifx_control_panel/ui/settings.py
lifx_control_panel/ui/splashscreen.py
lifx_control_panel/utilities/__init__.py
lifx_control_panel/utilities/async_bulb_interface.py
lifx_control_panel/utilities/audio.py
lifx_control_panel/utilities/color_thread.py
lifx_control_panel/utilities/keypress.py
lifx_control_panel/utilities/utils.py
lifx_control_panel-1.7.6.data/scripts/__main__.pyw
lifx_control_panel-1.7.6.dist-info/LICENSE.txt
lifx_control_panel-1.7.6.dist-info/METADATA
lifx_control_panel-1.7.6.dist-info/WHEEL
lifx_control_panel-1.7.6.dist-info/top_level.txt
lifx_control_panel-1.7.6.dist-info/RECORD
