Metadata-Version: 2.1
Name: lifx-control-panel
Version: 1.7.6
Summary: An open source application for controlling your LIFX brand lights
Home-page: http://github.com/samclane/LIFX-Control-Panel
Author: Sawyer McLane
Author-email: samclane@gmail.com
License: MIT
Download-URL: https://github.com/samclane/LIFX-Control-Panel/archive/1.7.6.tar.gz
Keywords: lifx,iot,smartbulb,smartlight,lan,application
Platform: UNKNOWN
Requires-Dist: PyHook3
Requires-Dist: desktopmagic
Requires-Dist: win32gui
Requires-Dist: pyaudio
Requires-Dist: Pillow
Requires-Dist: lifxlan
Requires-Dist: pywin32
Requires-Dist: numexpr
Requires-Dist: numpy
